mailchimp_transactional/__init__.py
mailchimp_transactional/api_client.py
mailchimp_transactional/api/__init__.py
mailchimp_transactional/api/allowlists_api.py
mailchimp_transactional/api/exports_api.py
mailchimp_transactional/api/inbound_api.py
mailchimp_transactional/api/ips_api.py
mailchimp_transactional/api/messages_api.py
mailchimp_transactional/api/metadata_api.py
mailchimp_transactional/api/rejects_api.py
mailchimp_transactional/api/senders_api.py
mailchimp_transactional/api/subaccounts_api.py
mailchimp_transactional/api/tags_api.py
mailchimp_transactional/api/templates_api.py
mailchimp_transactional/api/urls_api.py
mailchimp_transactional/api/users_api.py
mailchimp_transactional/api/webhooks_api.py
mailchimp_transactional/api/whitelists_api.py
mailchimp_transactional-1.0.49.dist-info/LICENSE
mailchimp_transactional-1.0.49.dist-info/METADATA
mailchimp_transactional-1.0.49.dist-info/WHEEL
mailchimp_transactional-1.0.49.dist-info/top_level.txt
mailchimp_transactional-1.0.49.dist-info/RECORD
