Metadata-Version: 2.1
Name: mailchimp-transactional
Version: 1.0.49
Summary: Mailchimp Transactional API
Home-page: UNKNOWN
Author: UNKNOWN
Author-email: apihelp@mailchimp.com
License: UNKNOWN
Keywords: Swagger,Mailchimp Transactional API
Platform: UNKNOWN
Requires-Dist: certifi (>=2017.4.17)
Requires-Dist: python-dateutil (>=2.1)
Requires-Dist: requests (>=2.23)
Requires-Dist: six (>=1.10)
Requires-Dist: urllib3 (>=1.23)
